{"cameraMode":{"drawMode":0,"name":"Shaded","section":"Shading Mode"},"sceneLighting":true,"audioPlay":false,"sceneViewState":{"showFog":true,"showMaterialUpdate":false,"showSkybox":true,"showFlares":true,"showImageEffects":true,"showParticleSystems":true},"in2DMode":false,"pivot":{"x":0.6800000071525574,"y":6.860000133514404,"z":0.27000001072883608},"rotation":{"x":-0.4936645030975342,"y":0.005736876744776964,"z":-0.0032570487819612028,"w":-0.8696298003196716},"size":13.238560676574707,"orthographic":false}